odoo/addons/web_widget_color/README.rst
odoo/addons/web_widget_color/__init__.py
odoo/addons/web_widget_color/__manifest__.py
odoo/addons/web_widget_color/i18n/web_widget_color.pot
odoo/addons/web_widget_color/i18n/zh_CN.po
odoo/addons/web_widget_color/images/form_view.png
odoo/addons/web_widget_color/images/list_view.png
odoo/addons/web_widget_color/images/picker.png
odoo/addons/web_widget_color/readme/CONTRIBUTORS.rst
odoo/addons/web_widget_color/readme/DESCRIPTION.rst
odoo/addons/web_widget_color/readme/USAGE.rst
odoo/addons/web_widget_color/static/description/icon.png
odoo/addons/web_widget_color/static/description/index.html
odoo/addons/web_widget_color/static/lib/jscolor/jscolor-example.html
odoo/addons/web_widget_color/static/lib/jscolor/jscolor.js
odoo/addons/web_widget_color/static/src/js/widget.js
odoo/addons/web_widget_color/static/src/scss/widget.scss
odoo/addons/web_widget_color/static/src/xml/widget.xml
odoo/addons/web_widget_color/view/web_widget_color_view.xml
odoo12_addon_web_widget_color-12.0.1.0.1.dist-info/METADATA
odoo12_addon_web_widget_color-12.0.1.0.1.dist-info/WHEEL
odoo12_addon_web_widget_color-12.0.1.0.1.dist-info/top_level.txt
odoo12_addon_web_widget_color-12.0.1.0.1.dist-info/RECORD
